npnlp/__init__.py
npnlp/_sqp.py
npnlp/npnlp.py
npnlp/release.py
npnlp/tests/test_sqp.py
npnlp-0.0.2.dist-info/LICENSE.txt
npnlp-0.0.2.dist-info/METADATA
npnlp-0.0.2.dist-info/WHEEL
npnlp-0.0.2.dist-info/top_level.txt
npnlp-0.0.2.dist-info/RECORD
